shodanfinder/script.py
shodanfinder/secret.py
shodanfinder/shodan_finder.py
shodanfinder/test.py
shodanfinder-1.4.3.dist-info/METADATA
shodanfinder-1.4.3.dist-info/WHEEL
shodanfinder-1.4.3.dist-info/top_level.txt
shodanfinder-1.4.3.dist-info/RECORD
