Metadata-Version: 2.1
Name: shodanfinder
Version: 1.4.3
Summary: Get an observation on any website on internet using Shodan
Home-page: https://github.com/elkarouani/shodan-finder-demo
Author: KDragon
Author-email: elkarouani@gmail.com
License: UNKNOWN
Platform: UNKNOWN
Classifier: Programming Language :: Python :: 3
Classifier: License :: OSI Approved :: MIT License
Classifier: Operating System :: OS Independent
Requires-Dist: bleach (==3.1.4)
Requires-Dist: certifi (==2019.11.28)
Requires-Dist: chardet (==3.0.4)
Requires-Dist: click (==7.1.1)
Requires-Dist: click-plugins (==1.1.1)
Requires-Dist: colorama (==0.4.3)
Requires-Dist: docutils (==0.16)
Requires-Dist: idna (==2.9)
Requires-Dist: importlib-metadata (==1.6.0)
Requires-Dist: keyring (==21.2.0)
Requires-Dist: lxml (==4.5.0)
Requires-Dist: Pillow (==7.1.1)
Requires-Dist: pkginfo (==1.5.0.1)
Requires-Dist: Pygments (==2.6.1)
Requires-Dist: python-docx (==0.8.10)
Requires-Dist: pywin32-ctypes (==0.2.0)
Requires-Dist: readme-renderer (==25.0)
Requires-Dist: requests (==2.23.0)
Requires-Dist: requests-toolbelt (==0.9.1)
Requires-Dist: shodan (==1.22.0)
Requires-Dist: six (==1.14.0)
Requires-Dist: tqdm (==4.45.0)
Requires-Dist: twine (==3.1.1)
Requires-Dist: urllib3 (==1.25.8)
Requires-Dist: webencodings (==0.5.1)
Requires-Dist: wincertstore (==0.2)
Requires-Dist: XlsxWriter (==1.2.8)
Requires-Dist: zipp (==3.1.0)
